zapp/__init__.py
zapp/arguments.py
zapp/behave/context.py
zapp/behave/runner.py
zapp/behave.ini
zapp/driver/__init__.py
zapp/driver/js_func.py
zapp/driver/models.py
zapp/driver/playwright/__init__.py
zapp/driver/playwright/factory.py
zapp/driver/playwright/js.py
zapp/driver/playwright/key_mappings.py
zapp/driver/selenium/__init__.py
zapp/driver/selenium/browser/__init__.py
zapp/driver/selenium/browser/base.py
zapp/driver/selenium/browser/chrome.py
zapp/driver/selenium/browser/chromium.py
zapp/driver/selenium/browser/edge.py
zapp/driver/selenium/browser/firefox.py
zapp/driver/selenium/browser/ie.py
zapp/driver/selenium/browser/safari.py
zapp/driver/selenium/browser/sber.py
zapp/driver/selenium/browser/yandex.py
zapp/driver/selenium/factory.py
zapp/driver/selenium/js.py
zapp/driver/strategies.py
zapp/features/__init__.py
zapp/features/core/__init__.py
zapp/features/core/allure_reporter/__init__.py
zapp/features/core/allure_reporter/allure_reporter.py
zapp/features/core/api.py
zapp/features/core/database.py
zapp/features/core/locators.py
zapp/features/core/logging.py
zapp/features/core/sessions/__init__.py
zapp/features/core/sessions/keycloak.py
zapp/features/core/settings.py
zapp/features/core/tms/__init__.py
zapp/features/core/tms/test_culture/__init__.py
zapp/features/core/tms/test_culture/context.py
zapp/features/core/tms/test_culture/reporter.py
zapp/features/core/tms/test_culture/utils.py
zapp/features/core/tms/zephyr/__init__.py
zapp/features/core/tms/zephyr/allure_integration.py
zapp/features/core/tms/zephyr/zephyr.py
zapp/features/core/tms/zephyr/zephyr_ext.py
zapp/features/core/utils.py
zapp/features/core/waits.py
zapp/features/environment.py
zapp/features/steps/__init__.py
zapp/features/steps/bundled/__init__.py
zapp/features/steps/bundled/api.py
zapp/features/steps/bundled/browser.py
zapp/features/steps/bundled/common.py
zapp/features/steps/bundled/db.py
zapp/features/steps/bundled/file.py
zapp/features/steps/bundled/session.py
sbt_zapp-3.13.4.dist-info/LICENSE
sbt_zapp-3.13.4.dist-info/METADATA
sbt_zapp-3.13.4.dist-info/WHEEL
sbt_zapp-3.13.4.dist-info/RECORD
