Metadata-Version: 2.3
Name: sbt-zapp
Version: 3.13.4
Summary: BDD-based framework for UI testing
License: MIT
Author: SberTech
Requires-Python: >=3.10,<4.0
Classifier: License :: OSI Approved :: MIT License
Classifier: Operating System :: OS Independent
Classifier: Programming Language :: Python :: 3
Classifier: Programming Language :: Python :: 3.10
Classifier: Programming Language :: Python :: 3.11
Classifier: Programming Language :: Python :: 3.12
Classifier: Programming Language :: Python :: 3.13
Requires-Dist: PyHamcrest (>=2.0.0,<2.1.0)
Requires-Dist: allure-behave (==2.13.5)
Requires-Dist: beautifulsoup4 (==4.13.4)
Requires-Dist: behave (==1.3.3)
Requires-Dist: behave-parallel-runners (==1.1.0)
Requires-Dist: colorlog (>=6.6.0,<7.0.0)
Requires-Dist: envparse (<0.3)
Requires-Dist: jsonschema (>=4.23.0,<5.0.0)
Requires-Dist: mimesis (==18.0.0)
Requires-Dist: playwright (==1.54)
Requires-Dist: py-postgresql (==1.2.2)
Requires-Dist: pyperclip (==1.9.0)
Requires-Dist: pyrate-limiter (==3.7.0)
Requires-Dist: requests (==2.32.3)
Requires-Dist: selene (==2.0.0rc9)
Requires-Dist: selenium (==4.35.0)
Requires-Dist: tenacity (==9.*)
Requires-Dist: test-culture-client (==1.3.0)
Requires-Dist: tzdata (>=2025.2,<2026.0)
Requires-Dist: validators (==0.18.2)
Requires-Dist: zephyr-python-api (==0.1.0)
Project-URL: Repository, https://gitverse.ru/sbertech/zapp
